{"curContainerId":"70d339d6-5be4-ceca-66ec-e9ebb9e7dd06","version":"8.3.0","containers":[{"__class":"Container","__uniqueId":"70d339d6-5be4-ceca-66ec-e9ebb9e7dd06","_IdentityId":"3fcfc484-ae4b-0e67-d2ac-5c979bf88e8e","_dataVersion":{"primaryVersion":"8.1.0","moduleVersion":[]},"graph":{"__class":"ScriptGraph","__uniqueId":"75511632-bb42-3b9b-5b64-a93ab418c6d1","_IdentityId":"24511287-7af0-adba-23f4-23035e9eb517","_dataVersion":{"primaryVersion":"8.1.0","moduleVersion":[]},"panelName":"可视化编程面板","graphType":"SCRIPT","nodeList":[{"__class":"ScriptTemplateNode","__uniqueId":"98700ca4-d960-9cbd-c559-cf7d3b08c2da","_IdentityId":"721b390c-2600-7acf-7145-e33f06c74236","_dataVersion":{"primaryVersion":"8.2.0","moduleVersion":[["CatFaceWarpXComponent","0.1.1"],["DogFaceWarpXComponent","0.1.1"],["FaceWarpXComponent","0.1.1"]]},"nodeType":"SCRIPT","position":{"x":50000,"y":49900},"name":"Update","owner":{"__referenceId":"75511632-bb42-3b9b-5b64-a93ab418c6d1"},"size":{"width":171,"height":92},"description":"Execute the next node in every frame.","category":"Event","deletable":true,"cloneable":true,"inputPorts":[],"outputPorts":[{"__class":"ScriptPort","__uniqueId":"8b758cee-503d-a29e-a16f-c7f3d9663b52","_IdentityId":"372dc16d-5dc2-0232-91cb-954ed670c09a","_dataVersion":{"primaryVersion":"8.2.0","moduleVersion":[["CatFaceWarpXComponent","0.1.1"],["DogFaceWarpXComponent","0.1.1"],["FaceWarpXComponent","0.1.1"]]},"portName":"Next","type":"CONTROL","isInput":false,"isConnected":false,"isDynamic":false,"centerPosition":{"x":50157,"y":49948},"valueTypeName":"Pulse","portIndex":0,"portValue":null,"visible":true,"refEdgeIds":[],"owner":{"__referenceId":"98700ca4-d960-9cbd-c559-cf7d3b08c2da"},"hideInput":false,"isArray":false,"singleValueType":"Default","generic":null,"valueList":[],"valueListKeys":[],"defaultValueList":[],"linkedIndex":-1,"linkedEvents":[],"linkedMessages":[],"addManually":false},{"__class":"ScriptPort","__uniqueId":"46ea9348-2fcb-0f0f-3238-9adf67a861ee","_IdentityId":"78bfffcb-c1e0-5929-f89e-55057e3ed0e2","_dataVersion":{"primaryVersion":"8.2.0","moduleVersion":[["CatFaceWarpXComponent","0.1.1"],["DogFaceWarpXComponent","0.1.1"],["FaceWarpXComponent","0.1.1"]]},"portName":"Delta Time","type":"DATA","isInput":false,"isConnected":false,"isDynamic":false,"centerPosition":{"x":50157,"y":49972},"valueTypeName":"Double","portIndex":1,"portValue":null,"visible":true,"refEdgeIds":[],"owner":{"__referenceId":"98700ca4-d960-9cbd-c559-cf7d3b08c2da"},"hideInput":false,"isArray":false,"singleValueType":"Default","generic":null,"valueList":[],"valueListKeys":[],"defaultValueList":[],"linkedIndex":-1,"linkedEvents":[],"linkedMessages":[],"addManually":false}],"error":false,"groupEnable":true,"renamable":false,"nodeSettings":[],"guid":"76dd06cb-6f7a-60eb-e2fa-c9b10a0c78fc","version":"1.0.1","dynamicMessages":[],"nodeName":"","curSelectedType":"","compatibleState":0},{"__class":"ScriptTemplateNode","__uniqueId":"98b86b27-1304-ec31-164d-199cbae809e2","_IdentityId":"e4757246-3c9b-ec7e-d03c-e1a34006d31d","_dataVersion":{"primaryVersion":"8.2.0","moduleVersion":[["CatFaceWarpXComponent","0.1.1"],["DogFaceWarpXComponent","0.1.1"],["FaceWarpXComponent","0.1.1"]]},"nodeType":"SCRIPT","position":{"x":50000,"y":50050},"name":"Start","owner":{"__referenceId":"75511632-bb42-3b9b-5b64-a93ab418c6d1"},"size":{"width":164,"height":84},"description":"Execute the next node when an effect starts.","category":"Event","deletable":true,"cloneable":true,"inputPorts":[],"outputPorts":[{"__class":"ScriptPort","__uniqueId":"1d5c7045-50e2-65ff-0355-06f6aa23a827","_IdentityId":"7834250d-1157-a1df-cb24-0c23c93e2629","_dataVersion":{"primaryVersion":"8.2.0","moduleVersion":[["CatFaceWarpXComponent","0.1.1"],["DogFaceWarpXComponent","0.1.1"],["FaceWarpXComponent","0.1.1"]]},"portName":"Next","type":"CONTROL","isInput":false,"isConnected":false,"isDynamic":false,"centerPosition":{"x":50150,"y":50098},"valueTypeName":"Pulse","portIndex":0,"portValue":null,"visible":true,"refEdgeIds":[],"owner":{"__referenceId":"98b86b27-1304-ec31-164d-199cbae809e2"},"hideInput":false,"isArray":false,"singleValueType":"Default","generic":null,"valueList":[],"valueListKeys":[],"defaultValueList":[],"linkedIndex":-1,"linkedEvents":[],"linkedMessages":[],"addManually":false}],"error":false,"groupEnable":true,"renamable":false,"nodeSettings":[],"guid":"2f0fed0f-5279-9602-3083-5e1fb8163563","version":"1.0.1","dynamicMessages":[],"nodeName":"","curSelectedType":"","compatibleState":0},{"__class":"ScriptTemplateNode","__uniqueId":"f0178ea2-eb57-f7b8-23cd-4f2ac92f9949","_IdentityId":"86b8f761-def2-f1d8-ab43-181acc08b4e2","_dataVersion":{"primaryVersion":"0.0.0","moduleVersion":[]},"nodeType":"SCRIPT","position":{"x":49888.5473970474,"y":50197.66219891221},"name":"Screen Image Tap","owner":{"__referenceId":"75511632-bb42-3b9b-5b64-a93ab418c6d1"},"size":{"width":260,"height":120},"description":"Execute next node when an input image is tapped.","category":"Utility","deletable":true,"cloneable":true,"inputPorts":[{"__class":"ScriptPort","__uniqueId":"c7689bb8-03bb-a9c7-87c3-7dcdce33628e","_IdentityId":"1163c2d4-f5d2-b396-eda2-4f9582a90916","_dataVersion":{"primaryVersion":"0.0.0","moduleVersion":[]},"portName":"Image","type":"DATA","isInput":true,"isConnected":false,"isDynamic":false,"centerPosition":{"x":49902.5473970474,"y":50295.66219891221},"valueTypeName":"Image","portIndex":0,"portValue":{"type":"Component","value":"Guid(5468194120191831883, 1073951639506001799)"},"visible":true,"refEdgeIds":[],"owner":{"__referenceId":"f0178ea2-eb57-f7b8-23cd-4f2ac92f9949"},"hideInput":false,"isArray":false,"singleValueType":"Default","generic":null,"valueList":[],"valueListKeys":[],"defaultValueList":[],"linkedIndex":-1,"linkedEvents":[],"linkedMessages":[],"addManually":false}],"outputPorts":[{"__class":"ScriptPort","__uniqueId":"d8c2260e-daa6-1bac-4970-a0f287dff215","_IdentityId":"80f7d055-476c-646f-bfca-079cad8eedb1","_dataVersion":{"primaryVersion":"0.0.0","moduleVersion":[]},"portName":"On Image Tapped","type":"CONTROL","isInput":false,"isConnected":true,"isDynamic":false,"centerPosition":{"x":50134.5473970474,"y":50245.66219891221},"valueTypeName":"Pulse","portIndex":0,"portValue":null,"visible":true,"refEdgeIds":["eb656b8c-bd6e-54fe-531d-b73c4f561c41"],"owner":{"__referenceId":"f0178ea2-eb57-f7b8-23cd-4f2ac92f9949"},"hideInput":false,"isArray":false,"singleValueType":"Default","generic":null,"valueList":[],"valueListKeys":[],"defaultValueList":[],"linkedIndex":-1,"linkedEvents":[],"linkedMessages":[],"addManually":false},{"__class":"ScriptPort","__uniqueId":"d505001b-dba1-12d9-21da-dfc178e252b2","_IdentityId":"dae7d5a9-c8ed-6ab2-f38c-4542454b5998","_dataVersion":{"primaryVersion":"0.0.0","moduleVersion":[]},"portName":"Is Tapped","type":"DATA","isInput":false,"isConnected":false,"isDynamic":false,"centerPosition":{"x":50134.5473970474,"y":50269.66219891221},"valueTypeName":"Bool","portIndex":1,"portValue":null,"visible":true,"refEdgeIds":[],"owner":{"__referenceId":"f0178ea2-eb57-f7b8-23cd-4f2ac92f9949"},"hideInput":false,"isArray":false,"singleValueType":"Default","generic":null,"valueList":[],"valueListKeys":[],"defaultValueList":[],"linkedIndex":-1,"linkedEvents":[],"linkedMessages":[],"addManually":false}],"error":false,"groupEnable":true,"renamable":false,"nodeSettings":[],"guid":"ad63330f-27b0-cb2a-e3ad-8d0bdf7ff86c","version":"1.0.0","dynamicMessages":[],"nodeName":"","curSelectedType":"","compatibleState":0},{"__class":"VariableNode","__uniqueId":"13011d3a-52df-b055-0b36-b272182f0b57","_IdentityId":"e8abaeb2-dd58-3f27-a505-996ab48f7fe0","_dataVersion":{"primaryVersion":"0.0.0","moduleVersion":[]},"nodeType":"SCRIPT","position":{"x":50065.8752913753,"y":50351.447552447564},"name":"placeArr","owner":{"__referenceId":"75511632-bb42-3b9b-5b64-a93ab418c6d1"},"size":{"width":178,"height":337},"description":"","category":"Variable","deletable":true,"cloneable":true,"inputPorts":[{"__class":"ScriptPort","__uniqueId":"dacaeb3c-478c-e8ca-10af-0d6930b980f8","_IdentityId":"96b4ee0c-8d43-9a0b-7e61-544c28d167a9","_dataVersion":{"primaryVersion":"0.0.0","moduleVersion":[]},"portName":"Set","type":"CONTROL","isInput":true,"isConnected":true,"isDynamic":false,"centerPosition":{"x":50079.8752913753,"y":50449.447552447564},"valueTypeName":"Pulse","portIndex":0,"portValue":{"type":"Pulse","value":false},"visible":true,"refEdgeIds":["eb656b8c-bd6e-54fe-531d-b73c4f561c41"],"owner":{"__referenceId":"13011d3a-52df-b055-0b36-b272182f0b57"},"hideInput":false,"isArray":false,"singleValueType":"Default","generic":null,"valueList":[],"valueListKeys":[],"defaultValueList":[],"linkedIndex":-1,"linkedEvents":[],"linkedMessages":[],"addManually":false},{"__class":"ScriptPort","__uniqueId":"73b2de9f-737c-8672-edef-270189cc1347","_IdentityId":"4a6ac2e2-85e5-146f-0b8e-3d35da598907","_dataVersion":{"primaryVersion":"0.0.0","moduleVersion":[]},"portName":"Value","type":"DATA","isInput":true,"isConnected":false,"isDynamic":false,"centerPosition":{"x":50079.8752913753,"y":50572.447552447564},"valueTypeName":"Array<Double>","portIndex":1,"portValue":{"type":"Number","value":[{"type":"Number","value":0},{"type":"Number","value":1},{"type":"Number","value":2},{"type":"Number","value":3},{"type":"Number","value":4},{"type":"Number","value":5}]},"visible":true,"refEdgeIds":[],"owner":{"__referenceId":"13011d3a-52df-b055-0b36-b272182f0b57"},"hideInput":false,"isArray":false,"singleValueType":"Default","generic":{"T":"T","curSelectType":"Double","originTypeName":"Array","curSelectTypeKey":"graph_type_number"},"valueList":[],"valueListKeys":[],"defaultValueList":[],"linkedIndex":-1,"linkedEvents":[],"linkedMessages":[],"addManually":false}],"outputPorts":[{"__class":"ScriptPort","__uniqueId":"6ee083b6-8e26-d890-4b15-c6e9a050d161","_IdentityId":"58816851-93ff-b675-b2ef-d6f4549720d7","_dataVersion":{"primaryVersion":"0.0.0","moduleVersion":[]},"portName":"Trigger","type":"CONTROL","isInput":false,"isConnected":false,"isDynamic":false,"centerPosition":{"x":50229.8752913753,"y":50399.447552447564},"valueTypeName":"Pulse","portIndex":0,"portValue":null,"visible":true,"refEdgeIds":[],"owner":{"__referenceId":"13011d3a-52df-b055-0b36-b272182f0b57"},"hideInput":false,"isArray":false,"singleValueType":"Default","generic":null,"valueList":[],"valueListKeys":[],"defaultValueList":[],"linkedIndex":-1,"linkedEvents":[],"linkedMessages":[],"addManually":false},{"__class":"ScriptPort","__uniqueId":"9648096e-4493-c80c-055a-f1b4405489df","_IdentityId":"468aeaad-f295-bc7c-009b-6caca70d16c4","_dataVersion":{"primaryVersion":"0.0.0","moduleVersion":[]},"portName":"Value","type":"DATA","isInput":false,"isConnected":true,"isDynamic":false,"centerPosition":{"x":50229.8752913753,"y":50423.447552447564},"valueTypeName":"Array<Double>","portIndex":1,"portValue":null,"visible":true,"refEdgeIds":["b70dc17c-d004-52e6-0fc0-64608851e3c5","d721ec9e-e2a0-f60e-de56-a05b340147ec","1c5db33e-4d66-5b93-5d53-5ff24b41a5c0","d4739a36-71cf-b6ba-c805-9f6041d6866a"],"owner":{"__referenceId":"13011d3a-52df-b055-0b36-b272182f0b57"},"hideInput":false,"isArray":false,"singleValueType":"Default","generic":{"T":"T","curSelectType":"Double","originTypeName":"Array","curSelectTypeKey":"graph_type_number"},"valueList":[],"valueListKeys":[],"defaultValueList":[],"linkedIndex":-1,"linkedEvents":[],"linkedMessages":[],"addManually":false}],"error":false,"groupEnable":true,"renamable":false,"nodeSettings":[],"guid":"","version":"1.0.0","dynamicMessages":[],"nodeName":"","accessType":"SETTER","variable":{"__class":"GraphVariable","__uniqueId":"54fae87b-33ea-6251-a6d8-708efe3bd809","_IdentityId":"4cd7daa1-3f04-79cc-42c6-7f41183020af","_dataVersion":{"primaryVersion":"0.0.0","moduleVersion":[]},"isPublic":false,"variableType":"Number","variableName":"placeArr","isLocal":false,"isArray":true,"arrayValue":[1,2,3,4,5,0],"owner":null,"settings":[{"key":"graph_details_basic_setting","property":[{"type":"String","section":"graph_details_basic_setting","key":"graph_details_basic_setting_name","value":"变量 0","attribute":{},"editable":true,"isTypeKey":false},{"type":"StringList","section":"graph_details_basic_setting","key":"graph_details_basic_setting_type","value":"Number","attribute":{"option":[{"key":"数值","value":"Number"},{"key":"布尔值","value":"Boolean"},{"key":"字符串","value":"String"},{"key":"颜色","value":"Color"},{"key":"二维向量","value":"Vec2"},{"key":"三维向量","value":"Vec3"},{"key":"四维向量","value":"Vec4"},{"key":"矩形","value":"Rect"},{"key":"纹理","value":"Texture"},{"key":"场景对象","value":"Scene Object"},{"key":"材质","value":"Material"},{"key":"组件","value":"Component"},{"key":"状态","value":"State"}]},"editable":true,"isTypeKey":false},{"type":"StringList","section":"graph_details_basic_setting","key":"graph_details_basic_setting_container","value":"Array","attribute":{"option":[{"key":"单独","value":"Single"},{"key":"数组","value":"Array"}]},"editable":true,"isTypeKey":false},{"type":"Value","section":"graph_details_basic_setting","key":"graph_details_basic_setting_default_value","value":{"_rtti":{}},"attribute":{"labelNumberOfLines":1,"eleAttr":{"fixSize":false,"addButtonName":"添加项"},"graphAttr":{"usedInGraph":true,"usedInVariable":true},"showDecimalZero":true,"accuracy":2,"expandHeader":true,"range":{"min":-1.7976931348623157e+308,"max":1.7976931348623157e+308},"numberType":"Decimal","numberBox":true},"editable":true,"otherProps":{"needHeader":true},"isTypeKey":false}]},{"key":"graph_details_ui_setting","property":[{"type":"String","section":"graph_details_ui_setting","key":"graph_details_ui_setting_array_element_name","value":"","editable":true,"isTypeKey":false}]}],"showInPanel":false,"propertiesData":[{"id":"dataType","data":{"type":"string","value":"Number"}},{"id":"isArray","data":{"type":"boolean","value":"Array"}},{"id":"initialValue","data":{"type":"any"}},{"id":"isCustomValueList","data":{"type":"boolean","value":false}},{"id":"customValueList","data":{"type":"vector","value":[]}},{"id":"isIntegrate","data":{"type":"boolean","value":false}},{"id":"arrayElementName","data":{"type":"string","value":""}},{"id":"isNumberMinEnabled","data":{"type":"boolean","value":false}},{"id":"numberMin","data":{"type":"number","value":0}},{"id":"isNumberMaxEnabled","data":{"type":"boolean","value":false}},{"id":"numberMax","data":{"type":"number","value":0}}],"isCloudSaveEnabled":false}},{"__class":"ScriptTemplateNode","__uniqueId":"19cffe69-2283-56e0-febd-0a1ef4d16235","_IdentityId":"cc30c5a5-acb5-39fa-530a-086522852262","_dataVersion":{"primaryVersion":"0.0.0","moduleVersion":[]},"nodeType":"SCRIPT","position":{"x":50349.12932328102,"y":50299.05673243917},"name":"Get Item from Array","owner":{"__referenceId":"75511632-bb42-3b9b-5b64-a93ab418c6d1"},"size":{"width":197,"height":120},"description":"Get a specific item from an array, supports all variables types.","category":"Utility","deletable":true,"cloneable":true,"inputPorts":[{"__class":"ScriptPort","__uniqueId":"505d879a-cc77-66ac-975c-06ff5e8b92ee","_IdentityId":"7ce140f3-eec4-6538-ef66-d988abf58a6f","_dataVersion":{"primaryVersion":"0.0.0","moduleVersion":[]},"portName":"Index","type":"DATA","isInput":true,"isConnected":false,"isDynamic":false,"centerPosition":{"x":50363.12932328102,"y":50373.05673243917},"valueTypeName":"Int","portIndex":0,"portValue":{"type":"Number","value":2},"visible":true,"refEdgeIds":[],"owner":{"__referenceId":"19cffe69-2283-56e0-febd-0a1ef4d16235"},"hideInput":false,"isArray":false,"singleValueType":"Default","generic":null,"valueList":[],"valueListKeys":[],"defaultValueList":[],"linkedIndex":-1,"linkedEvents":[],"linkedMessages":[],"addManually":false},{"__class":"ScriptPort","__uniqueId":"e5470603-486c-2197-decd-05dbeddc0eda","_IdentityId":"7b5304c4-e985-f6f3-c8d2-ea55804d7213","_dataVersion":{"primaryVersion":"0.0.0","moduleVersion":[]},"portName":"{dataType} Array","type":"DATA","isInput":true,"isConnected":true,"isDynamic":true,"centerPosition":{"x":50363.12932328102,"y":50399.05673243917},"valueTypeName":"Array<Double>","portIndex":1,"portValue":{"type":"","value":[]},"visible":true,"refEdgeIds":["b70dc17c-d004-52e6-0fc0-64608851e3c5"],"owner":{"__referenceId":"19cffe69-2283-56e0-febd-0a1ef4d16235"},"hideInput":false,"isArray":false,"singleValueType":"Default","generic":{"T":"T","curSelectType":"Double","originTypeName":"Array","curSelectTypeKey":"graph_type_number"},"valueList":[],"valueListKeys":[],"defaultValueList":[],"linkedIndex":-1,"linkedEvents":[],"linkedMessages":[],"addManually":false}],"outputPorts":[{"__class":"ScriptPort","__uniqueId":"c0186933-c7d9-9202-a430-f66efae9b894","_IdentityId":"0e7efb09-9bfd-28e7-b7c5-c91b9b4117f7","_dataVersion":{"primaryVersion":"0.0.0","moduleVersion":[]},"portName":"Item","type":"DATA","isInput":false,"isConnected":true,"isDynamic":true,"centerPosition":{"x":50532.12932328102,"y":50347.05673243917},"valueTypeName":"Double","portIndex":0,"portValue":null,"visible":true,"refEdgeIds":["65264f0c-73ff-eb6c-4db6-a4f844d4979c"],"owner":{"__referenceId":"19cffe69-2283-56e0-febd-0a1ef4d16235"},"hideInput":false,"isArray":false,"singleValueType":"Default","generic":null,"valueList":[],"valueListKeys":[],"defaultValueList":[],"linkedIndex":-1,"linkedEvents":[],"linkedMessages":[],"addManually":false}],"error":false,"groupEnable":true,"renamable":false,"nodeSettings":[],"guid":"834af7d5-45f8-a01d-7956-f3hxb9f77efa","version":"3.0.0","dynamicMessages":[],"nodeName":"","curSelectedType":"Double","compatibleState":0},{"__class":"ScriptTemplateNode","__uniqueId":"cfa1cdfe-18ab-cce3-4e80-af14938a1543","_IdentityId":"5b495eeb-bff5-cb48-bbb1-86f1db59ff58","_dataVersion":{"primaryVersion":"0.0.0","moduleVersion":[]},"nodeType":"SCRIPT","position":{"x":50268.35534747389,"y":50698.12337559492},"name":"Get Item from Array","owner":{"__referenceId":"75511632-bb42-3b9b-5b64-a93ab418c6d1"},"size":{"width":197,"height":120},"description":"Get a specific item from an array, supports all variables types.","category":"Utility","deletable":true,"cloneable":true,"inputPorts":[{"__class":"ScriptPort","__uniqueId":"5ded3a45-74ca-0e4c-d709-1d6975849181","_IdentityId":"c5b3cc1f-16d8-fc3e-531f-f91494f81f0b","_dataVersion":{"primaryVersion":"0.0.0","moduleVersion":[]},"portName":"Index","type":"DATA","isInput":true,"isConnected":false,"isDynamic":false,"centerPosition":{"x":50282.35534747389,"y":50772.12337559492},"valueTypeName":"Int","portIndex":0,"portValue":{"type":"Number","value":4},"visible":true,"refEdgeIds":[],"owner":{"__referenceId":"cfa1cdfe-18ab-cce3-4e80-af14938a1543"},"hideInput":false,"isArray":false,"singleValueType":"Default","generic":null,"valueList":[],"valueListKeys":[],"defaultValueList":[],"linkedIndex":-1,"linkedEvents":[],"linkedMessages":[],"addManually":false},{"__class":"ScriptPort","__uniqueId":"cb8566ea-709e-9d58-941c-dddb7d63d159","_IdentityId":"2550edb5-4bcd-1f7c-d9d8-6f171e35735c","_dataVersion":{"primaryVersion":"0.0.0","moduleVersion":[]},"portName":"{dataType} Array","type":"DATA","isInput":true,"isConnected":true,"isDynamic":true,"centerPosition":{"x":50282.35534747389,"y":50798.12337559492},"valueTypeName":"Array<Double>","portIndex":1,"portValue":{"type":"","value":[]},"visible":true,"refEdgeIds":["d4739a36-71cf-b6ba-c805-9f6041d6866a"],"owner":{"__referenceId":"cfa1cdfe-18ab-cce3-4e80-af14938a1543"},"hideInput":false,"isArray":false,"singleValueType":"Default","generic":{"T":"T","curSelectType":"Double","originTypeName":"Array","curSelectTypeKey":"graph_type_number"},"valueList":[],"valueListKeys":[],"defaultValueList":[],"linkedIndex":-1,"linkedEvents":[],"linkedMessages":[],"addManually":false}],"outputPorts":[{"__class":"ScriptPort","__uniqueId":"e70d9c74-6943-6d24-000d-2ec7aede11fd","_IdentityId":"2f5d1e90-85b9-12ef-a4e9-7dc9fd085ca6","_dataVersion":{"primaryVersion":"0.0.0","moduleVersion":[]},"portName":"Item","type":"DATA","isInput":false,"isConnected":true,"isDynamic":true,"centerPosition":{"x":50451.35534747389,"y":50746.12337559492},"valueTypeName":"Double","portIndex":0,"portValue":null,"visible":true,"refEdgeIds":["9cebc611-aa57-a402-a54c-140730286e72"],"owner":{"__referenceId":"cfa1cdfe-18ab-cce3-4e80-af14938a1543"},"hideInput":false,"isArray":false,"singleValueType":"Default","generic":null,"valueList":[],"valueListKeys":[],"defaultValueList":[],"linkedIndex":-1,"linkedEvents":[],"linkedMessages":[],"addManually":false}],"error":false,"groupEnable":true,"renamable":false,"nodeSettings":[],"guid":"834af7d5-45f8-a01d-7956-f3hxb9f77efa","version":"3.0.0","dynamicMessages":[],"nodeName":"","curSelectedType":"Double","compatibleState":0},{"__class":"ScriptTemplateNode","__uniqueId":"b79a68cc-4359-a4d7-694c-218d4421a289","_IdentityId":"f3b74669-7d95-4263-ffb5-215e0ff383df","_dataVersion":{"primaryVersion":"0.0.0","moduleVersion":[]},"nodeType":"SCRIPT","position":{"x":50621.406220654484,"y":50382.17917608144},"name":"Set Array Item Reference","owner":{"__referenceId":"75511632-bb42-3b9b-5b64-a93ab418c6d1"},"size":{"width":208,"height":200},"description":"Set a specific item in the Array by the index. It will replace the original reference Array's item.","category":"Utility","deletable":true,"cloneable":true,"inputPorts":[{"__class":"ScriptPort","__uniqueId":"efd178fa-9426-0da7-2e6b-22cde1bbc26c","_IdentityId":"7ea37494-293d-06ff-2117-dcebf975c232","_dataVersion":{"primaryVersion":"0.0.0","moduleVersion":[]},"portName":"Enter","type":"CONTROL","isInput":true,"isConnected":false,"isDynamic":false,"centerPosition":{"x":50635.406220654484,"y":50480.17917608144},"valueTypeName":"Pulse","portIndex":0,"portValue":{"type":"Pulse","value":false},"visible":true,"refEdgeIds":[],"owner":{"__referenceId":"b79a68cc-4359-a4d7-694c-218d4421a289"},"hideInput":false,"isArray":false,"singleValueType":"Default","generic":null,"valueList":[],"valueListKeys":[],"defaultValueList":[],"linkedIndex":-1,"linkedEvents":[],"linkedMessages":[],"addManually":false},{"__class":"ScriptPort","__uniqueId":"b3cdc393-cb4c-575b-443a-073677eb7258","_IdentityId":"ef12dac8-3441-9e44-06b5-4cfb490f4bb9","_dataVersion":{"primaryVersion":"0.0.0","moduleVersion":[]},"portName":"{dataType} Array","type":"DATA","isInput":true,"isConnected":true,"isDynamic":true,"centerPosition":{"x":50635.406220654484,"y":50506.17917608144},"valueTypeName":"Array<Double>","portIndex":1,"portValue":{"type":"","value":[]},"visible":true,"refEdgeIds":["d721ec9e-e2a0-f60e-de56-a05b340147ec"],"owner":{"__referenceId":"b79a68cc-4359-a4d7-694c-218d4421a289"},"hideInput":false,"isArray":false,"singleValueType":"Default","generic":{"T":"T","curSelectType":"Double","originTypeName":"Array","curSelectTypeKey":"graph_type_number"},"valueList":[],"valueListKeys":[],"defaultValueList":[],"linkedIndex":-1,"linkedEvents":[],"linkedMessages":[],"addManually":false},{"__class":"ScriptPort","__uniqueId":"54b6f2e4-8fe3-f5a5-01f1-b396e8d0fbd3","_IdentityId":"981b8455-43a6-cdd8-dd41-8ca869209051","_dataVersion":{"primaryVersion":"0.0.0","moduleVersion":[]},"portName":"Index","type":"DATA","isInput":true,"isConnected":false,"isDynamic":false,"centerPosition":{"x":50635.406220654484,"y":50532.17917608144},"valueTypeName":"Int","portIndex":2,"portValue":{"type":"Number","value":4},"visible":true,"refEdgeIds":[],"owner":{"__referenceId":"b79a68cc-4359-a4d7-694c-218d4421a289"},"hideInput":false,"isArray":false,"singleValueType":"Default","generic":null,"valueList":[],"valueListKeys":[],"defaultValueList":[],"linkedIndex":-1,"linkedEvents":[],"linkedMessages":[],"addManually":false},{"__class":"ScriptPort","__uniqueId":"04f7b7d3-ef87-d386-f3e8-fe63ddb3302c","_IdentityId":"e28722cd-1abf-975f-2df8-2c4256e7e973","_dataVersion":{"primaryVersion":"0.0.0","moduleVersion":[]},"portName":"Value","type":"DATA","isInput":true,"isConnected":true,"isDynamic":true,"centerPosition":{"x":50635.406220654484,"y":50560.17917608144},"valueTypeName":"Double","portIndex":3,"portValue":{"type":"Number","value":3},"visible":true,"refEdgeIds":["65264f0c-73ff-eb6c-4db6-a4f844d4979c"],"owner":{"__referenceId":"b79a68cc-4359-a4d7-694c-218d4421a289"},"hideInput":false,"isArray":false,"singleValueType":"Default","generic":null,"valueList":[],"valueListKeys":[],"defaultValueList":[],"linkedIndex":-1,"linkedEvents":[],"linkedMessages":[],"addManually":false}],"outputPorts":[{"__class":"ScriptPort","__uniqueId":"2d994f0c-0778-80f0-1792-46d6530f2f86","_IdentityId":"a880447a-3e91-449a-2c39-ecc5410f31fe","_dataVersion":{"primaryVersion":"0.0.0","moduleVersion":[]},"portName":"Next","type":"CONTROL","isInput":false,"isConnected":false,"isDynamic":false,"centerPosition":{"x":50815.406220654484,"y":50430.17917608144},"valueTypeName":"Pulse","portIndex":0,"portValue":null,"visible":true,"refEdgeIds":[],"owner":{"__referenceId":"b79a68cc-4359-a4d7-694c-218d4421a289"},"hideInput":false,"isArray":false,"singleValueType":"Default","generic":null,"valueList":[],"valueListKeys":[],"defaultValueList":[],"linkedIndex":-1,"linkedEvents":[],"linkedMessages":[],"addManually":false},{"__class":"ScriptPort","__uniqueId":"d22f741c-7dbb-f9c6-62c8-e04b4ad2affd","_IdentityId":"eaefad2a-d1aa-130b-d942-35884361ca9b","_dataVersion":{"primaryVersion":"0.0.0","moduleVersion":[]},"portName":"{dataType} Array","type":"DATA","isInput":false,"isConnected":false,"isDynamic":true,"centerPosition":{"x":50815.406220654484,"y":50454.17917608144},"valueTypeName":"Array<Double>","portIndex":1,"portValue":null,"visible":true,"refEdgeIds":[],"owner":{"__referenceId":"b79a68cc-4359-a4d7-694c-218d4421a289"},"hideInput":false,"isArray":false,"singleValueType":"Default","generic":{"T":"T","curSelectType":"Double","originTypeName":"Array","curSelectTypeKey":"graph_type_number"},"valueList":[],"valueListKeys":[],"defaultValueList":[],"linkedIndex":-1,"linkedEvents":[],"linkedMessages":[],"addManually":false}],"error":false,"groupEnable":true,"renamable":false,"nodeSettings":[],"guid":"1996f98c-da55-141a-4dbd-ba3fcd927c78","version":"2.0.0","dynamicMessages":[],"nodeName":"","curSelectedType":"Double","compatibleState":0},{"__class":"ScriptTemplateNode","__uniqueId":"150cce0e-795e-a0da-9b50-aa8d3b6b6e18","_IdentityId":"708dea8c-91d4-f635-0726-69df9ad5de8c","_dataVersion":{"primaryVersion":"0.0.0","moduleVersion":[]},"nodeType":"SCRIPT","position":{"x":50601.61571414692,"y":50621.78689747198},"name":"Set Array Item Reference","owner":{"__referenceId":"75511632-bb42-3b9b-5b64-a93ab418c6d1"},"size":{"width":208,"height":200},"description":"Set a specific item in the Array by the index. It will replace the original reference Array's item.","category":"Utility","deletable":true,"cloneable":true,"inputPorts":[{"__class":"ScriptPort","__uniqueId":"0c64b9cd-a43d-5c80-6b21-6c46b6da9b08","_IdentityId":"fde21185-fe0a-928e-12ee-9b8d0bdba285","_dataVersion":{"primaryVersion":"0.0.0","moduleVersion":[]},"portName":"Enter","type":"CONTROL","isInput":true,"isConnected":false,"isDynamic":false,"centerPosition":{"x":50615.61571414692,"y":50719.78689747198},"valueTypeName":"Pulse","portIndex":0,"portValue":{"type":"Pulse","value":false},"visible":true,"refEdgeIds":[],"owner":{"__referenceId":"150cce0e-795e-a0da-9b50-aa8d3b6b6e18"},"hideInput":false,"isArray":false,"singleValueType":"Default","generic":null,"valueList":[],"valueListKeys":[],"defaultValueList":[],"linkedIndex":-1,"linkedEvents":[],"linkedMessages":[],"addManually":false},{"__class":"ScriptPort","__uniqueId":"4e6e86a6-f358-942c-7478-288b60005b30","_IdentityId":"c017958d-f058-24d2-8558-2a3f37fe742e","_dataVersion":{"primaryVersion":"0.0.0","moduleVersion":[]},"portName":"{dataType} Array","type":"DATA","isInput":true,"isConnected":true,"isDynamic":true,"centerPosition":{"x":50615.61571414692,"y":50745.78689747198},"valueTypeName":"Array<Double>","portIndex":1,"portValue":{"type":"","value":[]},"visible":true,"refEdgeIds":["1c5db33e-4d66-5b93-5d53-5ff24b41a5c0"],"owner":{"__referenceId":"150cce0e-795e-a0da-9b50-aa8d3b6b6e18"},"hideInput":false,"isArray":false,"singleValueType":"Default","generic":{"T":"T","curSelectType":"Double","originTypeName":"Array","curSelectTypeKey":"graph_type_number"},"valueList":[],"valueListKeys":[],"defaultValueList":[],"linkedIndex":-1,"linkedEvents":[],"linkedMessages":[],"addManually":false},{"__class":"ScriptPort","__uniqueId":"e820d87f-b7d4-0e3f-ff4b-20b8ed6d676d","_IdentityId":"e901794c-13f3-136f-b103-c03b8ebb64b4","_dataVersion":{"primaryVersion":"0.0.0","moduleVersion":[]},"portName":"Index","type":"DATA","isInput":true,"isConnected":false,"isDynamic":false,"centerPosition":{"x":50615.61571414692,"y":50771.78689747198},"valueTypeName":"Int","portIndex":2,"portValue":{"type":"Number","value":2},"visible":true,"refEdgeIds":[],"owner":{"__referenceId":"150cce0e-795e-a0da-9b50-aa8d3b6b6e18"},"hideInput":false,"isArray":false,"singleValueType":"Default","generic":null,"valueList":[],"valueListKeys":[],"defaultValueList":[],"linkedIndex":-1,"linkedEvents":[],"linkedMessages":[],"addManually":false},{"__class":"ScriptPort","__uniqueId":"78a5042d-1814-79d8-78dc-fbda2c2ce4c2","_IdentityId":"71dde699-9111-21b5-705a-2bc8893ee72d","_dataVersion":{"primaryVersion":"0.0.0","moduleVersion":[]},"portName":"Value","type":"DATA","isInput":true,"isConnected":true,"isDynamic":true,"centerPosition":{"x":50615.61571414692,"y":50799.78689747198},"valueTypeName":"Double","portIndex":3,"portValue":{"type":"Number","value":5},"visible":true,"refEdgeIds":["9cebc611-aa57-a402-a54c-140730286e72"],"owner":{"__referenceId":"150cce0e-795e-a0da-9b50-aa8d3b6b6e18"},"hideInput":false,"isArray":false,"singleValueType":"Default","generic":null,"valueList":[],"valueListKeys":[],"defaultValueList":[],"linkedIndex":-1,"linkedEvents":[],"linkedMessages":[],"addManually":false}],"outputPorts":[{"__class":"ScriptPort","__uniqueId":"5a264bb2-87c9-b706-37ad-8b7f1124d445","_IdentityId":"5a7350bb-f94c-c8d9-6235-2c614c7bc17d","_dataVersion":{"primaryVersion":"0.0.0","moduleVersion":[]},"portName":"Next","type":"CONTROL","isInput":false,"isConnected":false,"isDynamic":false,"centerPosition":{"x":50795.61571414692,"y":50669.78689747198},"valueTypeName":"Pulse","portIndex":0,"portValue":null,"visible":true,"refEdgeIds":[],"owner":{"__referenceId":"150cce0e-795e-a0da-9b50-aa8d3b6b6e18"},"hideInput":false,"isArray":false,"singleValueType":"Default","generic":null,"valueList":[],"valueListKeys":[],"defaultValueList":[],"linkedIndex":-1,"linkedEvents":[],"linkedMessages":[],"addManually":false},{"__class":"ScriptPort","__uniqueId":"102ff057-decf-5cd3-ed75-6cbc045b198d","_IdentityId":"d1b14369-01cb-727b-1fdb-e3fae048313a","_dataVersion":{"primaryVersion":"0.0.0","moduleVersion":[]},"portName":"{dataType} Array","type":"DATA","isInput":false,"isConnected":false,"isDynamic":true,"centerPosition":{"x":50795.61571414692,"y":50693.78689747198},"valueTypeName":"Array<Double>","portIndex":1,"portValue":null,"visible":true,"refEdgeIds":[],"owner":{"__referenceId":"150cce0e-795e-a0da-9b50-aa8d3b6b6e18"},"hideInput":false,"isArray":false,"singleValueType":"Default","generic":{"T":"T","curSelectType":"Double","originTypeName":"Array","curSelectTypeKey":"graph_type_number"},"valueList":[],"valueListKeys":[],"defaultValueList":[],"linkedIndex":-1,"linkedEvents":[],"linkedMessages":[],"addManually":false}],"error":false,"groupEnable":true,"renamable":false,"nodeSettings":[],"guid":"1996f98c-da55-141a-4dbd-ba3fcd927c78","version":"2.0.0","dynamicMessages":[],"nodeName":"","curSelectedType":"Double","compatibleState":0}],"edgeList":[{"__class":"Edge","__uniqueId":"eb656b8c-bd6e-54fe-531d-b73c4f561c41","_IdentityId":"1cbf1a64-0bd9-e64b-1a2f-07aeab429d7a","_dataVersion":{"primaryVersion":"0.0.0","moduleVersion":[]},"owner":{"__referenceId":"75511632-bb42-3b9b-5b64-a93ab418c6d1"},"type":"BEZIER","sourcePortPosition":{"x":50134.5473970474,"y":50245.66219891221},"targetPortPosition":{"x":50079.8752913753,"y":50449.447552447564},"sourcePortId":"d8c2260e-daa6-1bac-4970-a0f287dff215","targetPortId":"dacaeb3c-478c-e8ca-10af-0d6930b980f8","isValid":true},{"__class":"Edge","__uniqueId":"b70dc17c-d004-52e6-0fc0-64608851e3c5","_IdentityId":"9ec28adf-0522-42f7-4d49-b8e30836b54f","_dataVersion":{"primaryVersion":"0.0.0","moduleVersion":[]},"owner":{"__referenceId":"75511632-bb42-3b9b-5b64-a93ab418c6d1"},"type":"BEZIER","sourcePortPosition":{"x":50229.8752913753,"y":50423.447552447564},"targetPortPosition":{"x":50363.12932328102,"y":50399.05673243917},"sourcePortId":"9648096e-4493-c80c-055a-f1b4405489df","targetPortId":"e5470603-486c-2197-decd-05dbeddc0eda","isValid":true},{"__class":"Edge","__uniqueId":"d721ec9e-e2a0-f60e-de56-a05b340147ec","_IdentityId":"733920f3-98be-61c4-932c-6ffccb55ea98","_dataVersion":{"primaryVersion":"0.0.0","moduleVersion":[]},"owner":{"__referenceId":"75511632-bb42-3b9b-5b64-a93ab418c6d1"},"type":"BEZIER","sourcePortPosition":{"x":50229.8752913753,"y":50423.447552447564},"targetPortPosition":{"x":50635.406220654484,"y":50506.17917608144},"sourcePortId":"9648096e-4493-c80c-055a-f1b4405489df","targetPortId":"b3cdc393-cb4c-575b-443a-073677eb7258","isValid":true},{"__class":"Edge","__uniqueId":"65264f0c-73ff-eb6c-4db6-a4f844d4979c","_IdentityId":"b9eed4a7-17de-6179-d33f-8658e4b84799","_dataVersion":{"primaryVersion":"0.0.0","moduleVersion":[]},"owner":{"__referenceId":"75511632-bb42-3b9b-5b64-a93ab418c6d1"},"type":"BEZIER","sourcePortPosition":{"x":50532.12932328102,"y":50347.05673243917},"targetPortPosition":{"x":50635.406220654484,"y":50560.17917608144},"sourcePortId":"c0186933-c7d9-9202-a430-f66efae9b894","targetPortId":"04f7b7d3-ef87-d386-f3e8-fe63ddb3302c","isValid":true},{"__class":"Edge","__uniqueId":"1c5db33e-4d66-5b93-5d53-5ff24b41a5c0","_IdentityId":"9fd087fa-fe74-a4fa-4009-d727b1818d51","_dataVersion":{"primaryVersion":"0.0.0","moduleVersion":[]},"owner":{"__referenceId":"75511632-bb42-3b9b-5b64-a93ab418c6d1"},"type":"BEZIER","sourcePortPosition":{"x":50229.8752913753,"y":50423.447552447564},"targetPortPosition":{"x":50615.61571414692,"y":50745.78689747198},"sourcePortId":"9648096e-4493-c80c-055a-f1b4405489df","targetPortId":"4e6e86a6-f358-942c-7478-288b60005b30","isValid":true},{"__class":"Edge","__uniqueId":"9cebc611-aa57-a402-a54c-140730286e72","_IdentityId":"c3d5109a-b473-85df-2281-a913b1106df9","_dataVersion":{"primaryVersion":"0.0.0","moduleVersion":[]},"owner":{"__referenceId":"75511632-bb42-3b9b-5b64-a93ab418c6d1"},"type":"BEZIER","sourcePortPosition":{"x":50451.35534747389,"y":50746.12337559492},"targetPortPosition":{"x":50615.61571414692,"y":50799.78689747198},"sourcePortId":"e70d9c74-6943-6d24-000d-2ec7aede11fd","targetPortId":"78a5042d-1814-79d8-78dc-fbda2c2ce4c2","isValid":true},{"__class":"Edge","__uniqueId":"d4739a36-71cf-b6ba-c805-9f6041d6866a","_IdentityId":"6cc32227-c884-6493-5c03-907a6f6fb4d1","_dataVersion":{"primaryVersion":"0.0.0","moduleVersion":[]},"owner":{"__referenceId":"75511632-bb42-3b9b-5b64-a93ab418c6d1"},"type":"BEZIER","sourcePortPosition":{"x":50229.8752913753,"y":50423.447552447564},"targetPortPosition":{"x":50282.35534747389,"y":50798.12337559492},"sourcePortId":"9648096e-4493-c80c-055a-f1b4405489df","targetPortId":"cb8566ea-709e-9d58-941c-dddb7d63d159","isValid":true}],"owner":{"__referenceId":"70d339d6-5be4-ceca-66ec-e9ebb9e7dd06"},"ui":{"editable":true,"transform":{"a":1.3378791641536831,"b":0,"c":0,"d":1.3378791641536831,"e":-67279.97085695223,"f":-67097.60094058828},"transformLocal":{"a":1.3378791641536831,"b":0,"c":0,"d":1.3378791641536831,"e":-67494.97085695223,"f":-67525.60094058828},"scaleTransformLocal":{"a":1,"b":0,"c":0,"d":1,"e":0,"f":0},"showMiniMap":false},"variableList":[{"__referenceId":"54fae87b-33ea-6251-a6d8-708efe3bd809"}],"localVariableList":[],"showVariablePanel":false,"showSubGraphPanel":false},"parent":null,"title":"主图","containerType":0}],"panelClosed":false,"panelCollapsed":false,"minimapOpen":false}